async_timer/__init__.py
async_timer/pacemaker.py
async_timer/timer.py
async_timer/traget_caller.py
mock_async_timer/__init__.py
mock_async_timer/timer.py
async_timer-1.1.6.dist-info/METADATA
async_timer-1.1.6.dist-info/WHEEL
async_timer-1.1.6.dist-info/RECORD
