Metadata-Version: 2.1
Name: async-timer
Version: 1.1.6
Summary: The missing Python async timer.
License: MIT
Keywords: async,timer
Author: Ilya O.
Author-email: vrghost@gmail.com
Requires-Python: >=3.8,<4.0
Classifier: Intended Audience :: Developers
Classifier: License :: OSI Approved :: MIT License
Classifier: Operating System :: OS Independent
Classifier: Programming Language :: Python :: 3
Classifier: Programming Language :: Python :: 3.8
Classifier: Programming Language :: Python :: 3.9
Classifier: Programming Language :: Python :: 3.10
Classifier: Programming Language :: Python :: 3.11
Classifier: Programming Language :: Python :: 3.12
Classifier: Topic :: Software Development :: Libraries
Project-URL: Source, https://github.com/VRGhost/async-timer
